{"cameraMode":{"drawMode":0,"name":"Shaded","section":"Shading Mode"},"sceneLighting":true,"audioPlay":false,"sceneViewState":{"m_AlwaysRefresh":false,"showFog":true,"showSkybox":true,"showFlares":true,"showImageEffects":true,"showParticleSystems":true,"showVisualEffectGraphs":true,"m_FxEnabled":true},"in2DMode":false,"pivot":{"x":-17.124252319335939,"y":10.164434432983399,"z":20.60296058654785},"rotation":{"x":-0.05778655409812927,"y":-0.25071361660957339,"z":-0.014847557991743088,"w":0.966402530670166},"size":24.7224178314209,"orthographic":false}